libvstruct2/__init__.py
libvstruct2/basefields.py
libvstruct2/defparser.py
libvstruct2/fileid.py
libvstruct2/logging.py
libvstruct2/vstruct.py
libvstruct2/defs/BMP.vs2
libvstruct2/defs/BMP.vs2.py
libvstruct2/defs/GIF.vs2
libvstruct2/defs/ICO.vs2
libvstruct2/defs/ICO.vs2.py
libvstruct2/defs/JPG.vs2
libvstruct2/defs/JPG.vs2.py
libvstruct2/defs/MBR.vs2
libvstruct2/defs/MBR.vs2.py
libvstruct2/defs/PDF.vs2
libvstruct2/defs/PE.vs2
libvstruct2/defs/PE.vs2.py
libvstruct2/defs/PNG.vs2
libvstruct2/defs/PNG.vs2.py
libvstruct2/defs/R1CS.vs2
libvstruct2/defs/R1CS.vs2.py
libvstruct2/defs/TIFF.vs2
libvstruct2/defs/TIFF.vs2.py
libvstruct2/defs/ZIP.vs2
libvstruct2/defs/ZIP.vs2.py
libvstruct2/defs/bios.vs2
libvstruct2/defs/bios.vs2.py
libvstruct2/defs/socks.vs2
libvstruct2/defs/zstd.vs2
libvstruct2/scripts/__init__.py
libvstruct2/scripts/s2.py
libvstruct2/vstructs/__init__.py
libvstruct2/vstructs/vs2_BMP.py
libvstruct2/vstructs/vs2_GIF.py
libvstruct2/vstructs/vs2_ICO.py
libvstruct2/vstructs/vs2_JPG.py
libvstruct2/vstructs/vs2_MBR.py
libvstruct2/vstructs/vs2_PDF.py
libvstruct2/vstructs/vs2_PE.py
libvstruct2/vstructs/vs2_PNG.py
libvstruct2/vstructs/vs2_R1CS.py
libvstruct2/vstructs/vs2_TIFF.py
libvstruct2/vstructs/vs2_ZIP.py
libvstruct2/vstructs/vs2_bios.py
libvstruct2/vstructs/vs2_socks.py
libvstruct2/vstructs/vs2_zstd.py
libvstruct2-2.0.5.dist-info/METADATA
libvstruct2-2.0.5.dist-info/WHEEL
libvstruct2-2.0.5.dist-info/entry_points.txt
libvstruct2-2.0.5.dist-info/licenses/LICENSE
libvstruct2-2.0.5.dist-info/RECORD
