Metadata-Version: 2.3
Name: libvstruct2
Version: 2.0.5
Summary: YAML-like structured binary data representation language (partially based on Python).
Project-URL: Homepage, https://gitlab.com/vtopan/libvstruct2
Author-email: Vlad Topan <vtopan@gmail.removethispart.com>
License: MIT License
License-File: LICENSE
Classifier: License :: OSI Approved :: MIT License
Classifier: Programming Language :: Python
Classifier: Programming Language :: Python :: 3
Requires-Python: >=3.9
